mandatum/__init__.py
mandatum/alerts.py
mandatum/display.py
mandatum/menu.py
mandatum/mode.py
mandatum/progress.py
mandatum/prompt.py
mandatum-1.3.0.dist-info/LICENSE
mandatum-1.3.0.dist-info/WHEEL
mandatum-1.3.0.dist-info/METADATA
mandatum-1.3.0.dist-info/RECORD
