Metadata-Version: 2.1
Name: mandatum
Version: 1.3.0
Summary: A python framework to make beatiful cli applications
Home-page: https://github.com/ZayedMalick/mandatum
License: MIT
Author: Zayed Malick
Author-email: zayedmalick13@gmail.com
Requires-Python: >=3.6,<4.0
Classifier: License :: OSI Approved :: MIT License
Classifier: Programming Language :: Python :: 3
Classifier: Programming Language :: Python :: 3.6
Classifier: Programming Language :: Python :: 3.7
Classifier: Programming Language :: Python :: 3.8
Classifier: Programming Language :: Python :: 3.9
Requires-Dist: rich (>=7.0.0,<8.0.0)
Project-URL: Repository, https://github.com/ZayedMalick/mandatum
